{
  "item": [
    {
      "id": "ce698eea-d5c8-4f0a-981b-2dfbbd797ab8",
      "name": "UPLOAD",
      "description": {
        "content": "Routes for upload",
        "type": "text/plain"
      },
      "item": [
        {
          "id": "7053d3b3-cc09-4c2f-8ba2-c1a2c7ccc40c",
          "name": "Create Item",
          "request": {
            "description": {
              "content": "Controller: uploadFile",
              "type": "text/markdown"
            },
            "url": {
              "path": [
                "upload"
              ],
              "host": [
                "{{base_url}}"
              ],
              "query": [],
              "variable": []
            },
            "method": "POST",
            "body": {}
          },
          "response": [],
          "event": []
        },
        {
          "id": "fd516f02-5940-433d-8617-dd444fb2236d",
          "name": "Delete Image",
          "request": {
            "description": {
              "content": "Controller: deleteUploadedFile\nSchema: deleteImageSchema\n\n### Validation Rules\n| Field | Type | Requirement |\n|---|---|---|\n| fileUrl | string | Required |\n",
              "type": "text/markdown"
            },
            "url": {
              "path": [
                "upload",
                "delete"
              ],
              "host": [
                "{{base_url}}"
              ],
              "query": [
                {
                  "key": "fileUrl",
                  "value": "sample_fileUrl"
                }
              ],
              "variable": []
            },
            "header": [
              {
                "key": "Content-Type",
                "value": "application/json"
              }
            ],
            "method": "DELETE",
            "body": {
              "mode": "raw",
              "raw": "{\n  \"fileUrl\": \"sample_fileUrl\"\n}"
            }
          },
          "response": [],
          "event": []
        },
        {
          "id": "77adb3cb-6aeb-41fa-b865-550f95f27048",
          "name": "Get Images",
          "request": {
            "description": {
              "content": "Controller: getAllImages",
              "type": "text/markdown"
            },
            "url": {
              "path": [
                "upload",
                "images"
              ],
              "host": [
                "{{base_url}}"
              ],
              "query": [],
              "variable": []
            },
            "method": "GET",
            "body": {}
          },
          "response": [],
          "event": []
        },
        {
          "id": "701cc896-276d-4210-acad-067f4f32ba24",
          "name": "Get Pdfs",
          "request": {
            "description": {
              "content": "Controller: getAllPdfs",
              "type": "text/markdown"
            },
            "url": {
              "path": [
                "upload",
                "pdfs"
              ],
              "host": [
                "{{base_url}}"
              ],
              "query": [],
              "variable": []
            },
            "method": "GET",
            "body": {}
          },
          "response": [],
          "event": []
        }
      ],
      "event": []
    },
    {
      "id": "bff04a20-7c04-49a8-a3d5-fc146b8f2fa9",
      "name": "PLAN",
      "description": {
        "content": "Routes for plan",
        "type": "text/plain"
      },
      "item": [
        {
          "id": "45c35764-f1e0-4f96-a64d-41d229a467a7",
          "name": "Create Plan",
          "request": {
            "description": {
              "content": "Controller: createPlan\nSchema: createPlanSchema\n\n### Validation Rules\n| Field | Type | Requirement |\n|---|---|---|\n| name | string | Required |\n| price | number | Required |\n| duration | string | Required |\n| features | array | Required |\n| isActive | boolean | Optional |\n",
              "type": "text/markdown"
            },
            "url": {
              "path": [
                "plan"
              ],
              "host": [
                "{{base_url}}"
              ],
              "query": [],
              "variable": []
            },
            "header": [
              {
                "key": "Content-Type",
                "value": "application/json"
              }
            ],
            "method": "POST",
            "body": {
              "mode": "raw",
              "raw": "{\n  \"name\": \"sample_name\",\n  \"price\": 123,\n  \"duration\": \"sample_duration\",\n  \"features\": [\n    \"sample_string\"\n  ],\n  \"isActive\": true\n}"
            }
          },
          "response": [],
          "event": []
        },
        {
          "id": "28bdf6c1-0828-4e27-9da5-057d443acb84",
          "name": "Plan Id",
          "request": {
            "description": {
              "content": "Controller: updatePlan\nSchema: planIdSchema\n\n### Validation Rules\n| Field | Type | Requirement |\n|---|---|---|\n| id | string | Required |\n",
              "type": "text/markdown"
            },
            "url": {
              "path": [
                "plan"
              ],
              "host": [
                "{{base_url}}"
              ],
              "query": [],
              "variable": []
            },
            "header": [
              {
                "key": "Content-Type",
                "value": "application/json"
              }
            ],
            "method": "PUT",
            "body": {
              "mode": "raw",
              "raw": "{\n  \"id\": \"sample_id\"\n}"
            }
          },
          "response": [],
          "event": []
        },
        {
          "id": "c4eed85e-e5ba-417a-aacd-b0d9866d0922",
          "name": "Plan Id",
          "request": {
            "description": {
              "content": "Controller: deletePlan\nSchema: planIdSchema\n\n### Validation Rules\n| Field | Type | Requirement |\n|---|---|---|\n| id | string | Required |\n",
              "type": "text/markdown"
            },
            "url": {
              "path": [
                "plan",
                ":id"
              ],
              "host": [
                "{{base_url}}"
              ],
              "query": [],
              "variable": [
                {
                  "type": "any",
                  "key": "id"
                },
                {
                  "type": "any",
                  "value": "sample_id",
                  "key": "id"
                }
              ]
            },
            "header": [
              {
                "key": "Content-Type",
                "value": "application/json"
              }
            ],
            "method": "DELETE",
            "body": {
              "mode": "raw",
              "raw": "{\n  \"id\": \"sample_id\"\n}"
            }
          },
          "response": [],
          "event": []
        },
        {
          "id": "dacf147b-94af-47c8-a16c-cb8296a4f5ba",
          "name": "Get Item",
          "request": {
            "description": {
              "content": "Controller: getPlans",
              "type": "text/markdown"
            },
            "url": {
              "path": [
                "plan"
              ],
              "host": [
                "{{base_url}}"
              ],
              "query": [],
              "variable": []
            },
            "method": "GET",
            "body": {}
          },
          "response": [],
          "event": []
        },
        {
          "id": "d9d8df63-90cb-4f26-8474-ff02a3940310",
          "name": "Plan Id",
          "request": {
            "description": {
              "content": "Controller: getPlanById\nSchema: planIdSchema\n\n### Validation Rules\n| Field | Type | Requirement |\n|---|---|---|\n| id | string | Required |\n",
              "type": "text/markdown"
            },
            "url": {
              "path": [
                "plan",
                ":id"
              ],
              "host": [
                "{{base_url}}"
              ],
              "query": [],
              "variable": [
                {
                  "type": "any",
                  "key": "id"
                },
                {
                  "type": "any",
                  "value": "sample_id",
                  "key": "id"
                }
              ]
            },
            "method": "GET",
            "body": {}
          },
          "response": [],
          "event": []
        }
      ],
      "event": [],
      "auth": {
        "type": "bearer",
        "bearer": [
          {
            "key": "TOKEN",
            "value": "{{TOKEN}}",
            "type": "string"
          }
        ]
      }
    },
    {
      "id": "46b47108-6907-464b-a9e7-83794f8d05ee",
      "name": "AUTH",
      "description": {
        "content": "Routes for auth",
        "type": "text/plain"
      },
      "item": [
        {
          "id": "572b143f-9720-48cf-84ff-174fd38c9fee",
          "name": "Signup",
          "request": {
            "description": {
              "content": "Controller: signup\nSchema: signupSchema\n\n### Validation Rules\n| Field | Type | Requirement |\n|---|---|---|\n| firstName | string | Required |\n| lastName | string | Required |\n| email | string | Required |\n| password | string | Required |\n| subscription | object | Optional |\n| subscription.planId | string | Optional |\n| subscription.type | string | Required |\n| subscription.status | string | Required |\n| subscription.startDate | date | Required |\n| subscription.endDate | date | Optional |\n| subscription.autoRenew | boolean | Required |\n",
              "type": "text/markdown"
            },
            "url": {
              "path": [
                "auth",
                "signup"
              ],
              "host": [
                "{{base_url}}"
              ],
              "query": [],
              "variable": []
            },
            "header": [
              {
                "key": "Content-Type",
                "value": "application/json"
              }
            ],
            "method": "POST",
            "body": {
              "mode": "raw",
              "raw": "{\n  \"firstName\": \"sample_firstName\",\n  \"lastName\": \"sample_lastName\",\n  \"email\": \"test@example.com\",\n  \"password\": \"Password123!\",\n  \"subscription\": {\n    \"planId\": \"sample_planId\",\n    \"type\": \"sample_type\",\n    \"status\": \"sample_status\",\n    \"startDate\": \"\",\n    \"endDate\": \"\",\n    \"autoRenew\": true\n  },\n  \"name\": \"sample_name\",\n  \"countryCode\": \"sample_countryCode\",\n  \"contact\": {\n    \"countryCode\": \"sample_countryCode\",\n    \"phoneNo\": \"sample_string\"\n  }\n}"
            }
          },
          "response": [],
          "event": []
        },
        {
          "id": "ddde9eb2-3db4-4c50-a339-ef7146ba7de8",
          "name": "Login",
          "request": {
            "description": {
              "content": "Controller: login\nSchema: loginSchema\n\n### Validation Rules\n| Field | Type | Requirement |\n|---|---|---|\n| email | string | Required |\n| password | string | Required |\n",
              "type": "text/markdown"
            },
            "url": {
              "path": [
                "auth",
                "login"
              ],
              "host": [
                "{{base_url}}"
              ],
              "query": [],
              "variable": []
            },
            "header": [
              {
                "key": "Content-Type",
                "value": "application/json"
              }
            ],
            "method": "POST",
            "body": {
              "mode": "raw",
              "raw": "{\n  \"email\": \"test@example.com\",\n  \"password\": \"Password123!\"\n}"
            }
          },
          "response": [],
          "event": []
        },
        {
          "id": "c044015a-3792-440f-900f-b90b9be9f3af",
          "name": "Verify Login Otp",
          "request": {
            "description": {
              "content": "Controller: verifyOtp\nSchema: verifyLoginOtpSchema\n\n### Validation Rules\n| Field | Type | Requirement |\n|---|---|---|\n| email | string | Required |\n| otp | number | Required |\n",
              "type": "text/markdown"
            },
            "url": {
              "path": [
                "auth",
                "verify-otp"
              ],
              "host": [
                "{{base_url}}"
              ],
              "query": [],
              "variable": []
            },
            "header": [
              {
                "key": "Content-Type",
                "value": "application/json"
              }
            ],
            "method": "POST",
            "body": {
              "mode": "raw",
              "raw": "{\n  \"email\": \"test@example.com\",\n  \"otp\": 123\n}"
            }
          },
          "response": [],
          "event": []
        },
        {
          "id": "31386d85-6b4a-4f68-913c-b5602ab79282",
          "name": "Forgot Password",
          "request": {
            "description": {
              "content": "Controller: forgotPassword\nSchema: forgotPasswordSchema\n\n### Validation Rules\n| Field | Type | Requirement |\n|---|---|---|\n| email | string | Required |\n",
              "type": "text/markdown"
            },
            "url": {
              "path": [
                "auth",
                "forgot-password"
              ],
              "host": [
                "{{base_url}}"
              ],
              "query": [],
              "variable": []
            },
            "header": [
              {
                "key": "Content-Type",
                "value": "application/json"
              }
            ],
            "method": "POST",
            "body": {
              "mode": "raw",
              "raw": "{\n  \"email\": \"test@example.com\"\n}"
            }
          },
          "response": [],
          "event": []
        },
        {
          "id": "be879f56-2b7a-4207-8319-650a4d99dd81",
          "name": "Reset Password",
          "request": {
            "description": {
              "content": "Controller: resetPassword\nSchema: resetPasswordSchema\n\n### Validation Rules\n| Field | Type | Requirement |\n|---|---|---|\n| email | string | Required |\n| otp | number | Required |\n| password | string | Required |\n",
              "type": "text/markdown"
            },
            "url": {
              "path": [
                "auth",
                "reset-password"
              ],
              "host": [
                "{{base_url}}"
              ],
              "query": [],
              "variable": []
            },
            "header": [
              {
                "key": "Content-Type",
                "value": "application/json"
              }
            ],
            "method": "POST",
            "body": {
              "mode": "raw",
              "raw": "{\n  \"email\": \"test@example.com\",\n  \"otp\": 123,\n  \"password\": \"Password123!\"\n}"
            }
          },
          "response": [],
          "event": []
        },
        {
          "id": "0d2a4b53-fa68-4b36-8cd4-c6822528be3c",
          "name": "Change Password",
          "request": {
            "description": {
              "content": "Controller: changePassword\nSchema: changePasswordSchema\n\n### Validation Rules\n| Field | Type | Requirement |\n|---|---|---|\n| oldPassword | string | Required |\n| newPassword | string | Required |\n",
              "type": "text/markdown"
            },
            "url": {
              "path": [
                "auth",
                "change-password"
              ],
              "host": [
                "{{base_url}}"
              ],
              "query": [],
              "variable": []
            },
            "header": [
              {
                "key": "Content-Type",
                "value": "application/json"
              }
            ],
            "method": "POST",
            "body": {
              "mode": "raw",
              "raw": "{\n  \"oldPassword\": \"Password123!\",\n  \"newPassword\": \"Password123!\",\n  \"email\": \"test@example.com\",\n  \"otp\": 123\n}"
            }
          },
          "response": [],
          "event": []
        },
        {
          "id": "ca508071-13f6-41c3-867f-0301fbe6ee65",
          "name": "Create Logout",
          "request": {
            "description": {
              "content": "Controller: logout",
              "type": "text/markdown"
            },
            "url": {
              "path": [
                "auth",
                "logout"
              ],
              "host": [
                "{{base_url}}"
              ],
              "query": [],
              "variable": []
            },
            "method": "POST",
            "body": {}
          },
          "response": [],
          "event": []
        }
      ],
      "event": [],
      "auth": {
        "type": "bearer",
        "bearer": [
          {
            "key": "TOKEN",
            "value": "{{TOKEN}}",
            "type": "string"
          }
        ]
      }
    },
    {
      "id": "2ab2cefd-2034-42a3-b7fe-49aee199dfab",
      "name": "USER",
      "description": {
        "content": "Routes for user",
        "type": "text/plain"
      },
      "item": [
        {
          "id": "bfd2145e-60d2-407c-a4ad-87873cecfed9",
          "name": "Get All Users Query",
          "request": {
            "description": {
              "content": "Controller: getAllUsers\nSchema: getAllUsersQuerySchema\n\n### Validation Rules\n| Field | Type | Requirement |\n|---|---|---|\n| page | number | Optional |\n| limit | number | Optional |\n| search | string | Optional |\n| activeFilter | boolean | Optional |\n| sortFilter | string | Optional |\n| startDateFilter | date | Optional |\n| endDateFilter | date | Optional |\n",
              "type": "text/markdown"
            },
            "url": {
              "path": [
                "user"
              ],
              "host": [
                "{{base_url}}"
              ],
              "query": [
                {
                  "key": "page",
                  "value": "1"
                },
                {
                  "key": "limit",
                  "value": "10"
                },
                {
                  "key": "search",
                  "value": "sample_search"
                },
                {
                  "key": "activeFilter",
                  "value": "true"
                },
                {
                  "key": "sortFilter",
                  "value": "sample_sortFilter"
                },
                {
                  "key": "startDateFilter",
                  "value": ""
                },
                {
                  "key": "endDateFilter",
                  "value": ""
                }
              ],
              "variable": []
            },
            "method": "GET",
            "body": {}
          },
          "response": [],
          "event": []
        },
        {
          "id": "f08cfe84-51c3-40ab-af31-2d3aa82dc56b",
          "name": "User Id",
          "request": {
            "description": {
              "content": "Controller: getUserById\nSchema: userIdSchema\n\n### Validation Rules\n| Field | Type | Requirement |\n|---|---|---|\n| id | string | Required |\n",
              "type": "text/markdown"
            },
            "url": {
              "path": [
                "user",
                ":id"
              ],
              "host": [
                "{{base_url}}"
              ],
              "query": [],
              "variable": [
                {
                  "type": "any",
                  "key": "id"
                },
                {
                  "type": "any",
                  "value": "sample_id",
                  "key": "id"
                }
              ]
            },
            "method": "GET",
            "body": {}
          },
          "response": [],
          "event": []
        },
        {
          "id": "3583307f-4531-4501-8f07-5937f97c0729",
          "name": "User Id",
          "request": {
            "description": {
              "content": "Controller: updateUser\nSchema: userIdSchema\n\n### Validation Rules\n| Field | Type | Requirement |\n|---|---|---|\n| id | string | Required |\n",
              "type": "text/markdown"
            },
            "url": {
              "path": [
                "user",
                ":id"
              ],
              "host": [
                "{{base_url}}"
              ],
              "query": [],
              "variable": [
                {
                  "type": "any",
                  "key": "id"
                },
                {
                  "type": "any",
                  "value": "sample_id",
                  "key": "id"
                }
              ]
            },
            "header": [
              {
                "key": "Content-Type",
                "value": "application/json"
              }
            ],
            "method": "PUT",
            "body": {
              "mode": "raw",
              "raw": "{\n  \"id\": \"sample_id\"\n}"
            }
          },
          "response": [],
          "event": []
        }
      ],
      "event": [],
      "auth": {
        "type": "bearer",
        "bearer": [
          {
            "key": "TOKEN",
            "value": "{{TOKEN}}",
            "type": "string"
          }
        ]
      }
    },
    {
      "id": "c4b633bb-7c39-4ab4-bd38-c2d6926b2719",
      "name": "STORE",
      "description": {
        "content": "Routes for store",
        "type": "text/plain"
      },
      "item": [
        {
          "id": "1732988a-f50f-45fc-9713-9c82ff97988c",
          "name": "Create Store",
          "request": {
            "description": {
              "content": "Controller: createStore\nSchema: createStoreSchema\n\n### Validation Rules\n| Field | Type | Requirement |\n|---|---|---|\n| name | string | Required |\n| slug | string | Required |\n| description | string | Optional |\n| logo | string | Optional |\n| banner | string | Optional |\n| userId | string | Optional |\n| subdomain | string | Required |\n| customDomain | string | Optional |\n| domainVerified | boolean | Optional |\n| isActive | boolean | Optional |\n| isPublished | boolean | Optional |\n| isBlocked | boolean | Optional |\n| businessName | string | Required |\n| businessType | string | Required |\n| gstNumber | string | Optional |\n| panNumber | string | Optional |\n| kycStatus | string | Optional |\n| kycDocuments | array | Optional |\n| kycDocuments[].type | string | Required |\n| kycDocuments[].documentUrl | string | Required |\n| kycDocuments[].verified | boolean | Optional |\n| address | object | Required |\n| address.country | string | Required |\n| address.state | string | Required |\n| address.city | string | Required |\n| address.pincode | string | Required |\n| address.addressLine1 | string | Required |\n| address.addressLine2 | string | Optional |\n| address.landmark | string | Optional |\n| email | string | Required |\n| phone | string | Required |\n| totalProducts | number | Optional |\n| totalOrders | number | Optional |\n| totalRevenue | number | Optional |\n",
              "type": "text/markdown"
            },
            "url": {
              "path": [
                "store"
              ],
              "host": [
                "{{base_url}}"
              ],
              "query": [],
              "variable": []
            },
            "header": [
              {
                "key": "Content-Type",
                "value": "application/json"
              }
            ],
            "method": "POST",
            "body": {
              "mode": "raw",
              "raw": "{\n  \"name\": \"sample_name\",\n  \"slug\": \"sample_slug\",\n  \"description\": \"sample_description\",\n  \"logo\": \"sample_logo\",\n  \"banner\": \"sample_banner\",\n  \"userId\": \"sample_userId\",\n  \"subdomain\": \"sample_subdomain\",\n  \"customDomain\": \"sample_customDomain\",\n  \"domainVerified\": true,\n  \"isActive\": true,\n  \"isPublished\": true,\n  \"isBlocked\": true,\n  \"businessName\": \"sample_businessName\",\n  \"businessType\": \"sample_businessType\",\n  \"gstNumber\": \"sample_gstNumber\",\n  \"panNumber\": \"sample_panNumber\",\n  \"kycStatus\": \"sample_kycStatus\",\n  \"kycDocuments\": [\n    {\n      \"type\": \"sample_type\",\n      \"documentUrl\": \"sample_documentUrl\",\n      \"verified\": true\n    }\n  ],\n  \"address\": {\n    \"country\": \"sample_country\",\n    \"state\": \"sample_state\",\n    \"city\": \"sample_city\",\n    \"pincode\": \"sample_pincode\",\n    \"addressLine1\": \"sample_addressLine1\",\n    \"addressLine2\": \"sample_addressLine2\",\n    \"landmark\": \"sample_landmark\"\n  },\n  \"email\": \"test@example.com\",\n  \"phone\": \"sample_phone\",\n  \"totalProducts\": 123,\n  \"totalOrders\": 123,\n  \"totalRevenue\": 123\n}"
            }
          },
          "response": [],
          "event": []
        },
        {
          "id": "ad286786-fbaa-4822-b540-7cfefcdd85dd",
          "name": "Store Id",
          "request": {
            "description": {
              "content": "Controller: updateStore\nSchema: storeIdSchema\n\n### Validation Rules\n| Field | Type | Requirement |\n|---|---|---|\n| id | string | Required |\n",
              "type": "text/markdown"
            },
            "url": {
              "path": [
                "store"
              ],
              "host": [
                "{{base_url}}"
              ],
              "query": [],
              "variable": []
            },
            "header": [
              {
                "key": "Content-Type",
                "value": "application/json"
              }
            ],
            "method": "PUT",
            "body": {
              "mode": "raw",
              "raw": "{\n  \"id\": \"sample_id\"\n}"
            }
          },
          "response": [],
          "event": []
        },
        {
          "id": "0c3f9544-e594-4914-8640-f73fd481af9d",
          "name": "Store Id",
          "request": {
            "description": {
              "content": "Controller: deleteStore\nSchema: storeIdSchema\n\n### Validation Rules\n| Field | Type | Requirement |\n|---|---|---|\n| id | string | Required |\n",
              "type": "text/markdown"
            },
            "url": {
              "path": [
                "store",
                ":id"
              ],
              "host": [
                "{{base_url}}"
              ],
              "query": [],
              "variable": [
                {
                  "type": "any",
                  "key": "id"
                },
                {
                  "type": "any",
                  "value": "sample_id",
                  "key": "id"
                }
              ]
            },
            "header": [
              {
                "key": "Content-Type",
                "value": "application/json"
              }
            ],
            "method": "DELETE",
            "body": {
              "mode": "raw",
              "raw": "{\n  \"id\": \"sample_id\"\n}"
            }
          },
          "response": [],
          "event": []
        },
        {
          "id": "ce437525-ee56-488b-859e-a1613195384b",
          "name": "Get All Stores Query",
          "request": {
            "description": {
              "content": "Controller: getStores\nSchema: getAllStoresQuerySchema\n\n### Validation Rules\n| Field | Type | Requirement |\n|---|---|---|\n| page | number | Optional |\n| limit | number | Optional |\n| search | string | Optional |\n| activeFilter | boolean | Optional |\n| isPublishedFilter | boolean | Optional |\n| isBlockedFilter | boolean | Optional |\n| kycStatusFilter | string | Optional |\n| userId | string | Optional |\n| sortFilter | string | Optional |\n| startDateFilter | date | Optional |\n| endDateFilter | date | Optional |\n",
              "type": "text/markdown"
            },
            "url": {
              "path": [
                "store"
              ],
              "host": [
                "{{base_url}}"
              ],
              "query": [
                {
                  "key": "page",
                  "value": "1"
                },
                {
                  "key": "limit",
                  "value": "10"
                },
                {
                  "key": "search",
                  "value": "sample_search"
                },
                {
                  "key": "activeFilter",
                  "value": "true"
                },
                {
                  "key": "isPublishedFilter",
                  "value": "true"
                },
                {
                  "key": "isBlockedFilter",
                  "value": "true"
                },
                {
                  "key": "kycStatusFilter",
                  "value": "sample_kycStatusFilter"
                },
                {
                  "key": "userId",
                  "value": "sample_userId"
                },
                {
                  "key": "sortFilter",
                  "value": "sample_sortFilter"
                },
                {
                  "key": "startDateFilter",
                  "value": ""
                },
                {
                  "key": "endDateFilter",
                  "value": ""
                }
              ],
              "variable": []
            },
            "method": "GET",
            "body": {}
          },
          "response": [],
          "event": []
        },
        {
          "id": "e479199c-fb4c-4345-b634-e4592c94ff6b",
          "name": "Store Id",
          "request": {
            "description": {
              "content": "Controller: getStoreById\nSchema: storeIdSchema\n\n### Validation Rules\n| Field | Type | Requirement |\n|---|---|---|\n| id | string | Required |\n",
              "type": "text/markdown"
            },
            "url": {
              "path": [
                "store",
                ":id"
              ],
              "host": [
                "{{base_url}}"
              ],
              "query": [],
              "variable": [
                {
                  "type": "any",
                  "key": "id"
                },
                {
                  "type": "any",
                  "value": "sample_id",
                  "key": "id"
                }
              ]
            },
            "method": "GET",
            "body": {}
          },
          "response": [],
          "event": []
        }
      ],
      "event": [],
      "auth": {
        "type": "bearer",
        "bearer": [
          {
            "key": "TOKEN",
            "value": "{{TOKEN}}",
            "type": "string"
          }
        ]
      }
    },
    {
      "id": "cc64ebd0-c31a-4690-b601-cff9974d9978",
      "name": "SETTING",
      "description": {
        "content": "Routes for setting",
        "type": "text/plain"
      },
      "item": [
        {
          "id": "bd5d044c-9986-4922-b42c-39c8b2813c18",
          "name": "Get Item",
          "request": {
            "description": {
              "content": "Controller: getSetting",
              "type": "text/markdown"
            },
            "url": {
              "path": [
                "setting"
              ],
              "host": [
                "{{base_url}}"
              ],
              "query": [],
              "variable": []
            },
            "method": "GET",
            "body": {}
          },
          "response": [],
          "event": []
        },
        {
          "id": "fd3204c1-9fb0-418e-94b7-501c9f276e53",
          "name": "Create Item",
          "request": {
            "description": {
              "content": "Controller: upsertSetting",
              "type": "text/markdown"
            },
            "url": {
              "path": [
                "setting"
              ],
              "host": [
                "{{base_url}}"
              ],
              "query": [],
              "variable": []
            },
            "method": "POST",
            "body": {}
          },
          "response": [],
          "event": []
        }
      ],
      "event": [],
      "auth": {
        "type": "bearer",
        "bearer": [
          {
            "key": "TOKEN",
            "value": "{{TOKEN}}",
            "type": "string"
          }
        ]
      }
    }
  ],
  "event": [],
  "variable": [
    {
      "type": "any",
      "value": "http://localhost:7782",
      "key": "base_url"
    },
    {
      "type": "any",
      "value": "http://localhost:7782",
      "key": "BASE_URL"
    },
    {
      "type": "any",
      "value": "",
      "key": "TOKEN"
    }
  ],
  "info": {
    "_postman_id": "704ee9ca-dfb6-46f4-8e08-aee5d3db8d04",
    "name": "HKDigiverse API",
    "schema": "https://schema.getpostman.com/json/collection/v2.1.0/collection.json",
    "description": {
      "content": "Auto generated API collection",
      "type": "text/plain"
    }
  }
}